<config><fields name="params"><fields name="data">
					<field type="bindingSource" readonly="false" label="bindingSource" default=""
						   name="bindingSource"

												>
											</field>
					<field type="checkbox" label="bindingSource" default="0"
						   name="enable_bindingsource" onchange="">

					</field>

									</fields>				<fields name="element_config">
					<field type="text" readonly="false" label="Icon left" default=""
						   name="group_add_on_left"

												>
											</field>
					<field type="checkbox" label="Icon left" default="0"
						   name="enable_group_add_on_left" onchange="">

					</field>

									
					<field type="text" readonly="false" label="Icon right" default=""
						   name="group_add_on_right"

												>
											</field>
					<field type="checkbox" label="Icon right" default="0"
						   name="enable_group_add_on_right" onchange="">

					</field>

									
					<field type="text" readonly="false" label="Default value" default=""
						   name="text"

												>
											</field>
					<field type="checkbox" label="Default value" default="0"
						   name="enable_text" onchange="">

					</field>

									
					<field type="text" readonly="false" label="Place holder" default=""
						   name="placeholder"

												>
											</field>
					<field type="checkbox" label="Place holder" default="0"
						   name="enable_placeholder" onchange="">

					</field>

									
					<field type="fieldnamebindingsourceselect2" readonly="false" label="Input name" default=""
						   name="name"

												>
											</field>
					<field type="checkbox" label="Input name" default="0"
						   name="enable_name" onchange="">

					</field>

									
					<field type="inputmask" readonly="false" label="Config update inputmask" default=""
						   name="config_update_inputmask"

												>
											</field>
					<field type="checkbox" label="Config update inputmask" default="0"
						   name="enable_config_update_inputmask" onchange="">

					</field>

									<fields name="element_required">
					<field type="radioyesno" readonly="false" label="required" default=""
						   name="required"

												>
											</field>
					<field type="checkbox" label="required" default="0"
						   name="enable_required" onchange="">

					</field>

									
					<field type="textarea" readonly="false" label="message" default="This field is required"
						   name="message"

												>
											</field>
					<field type="checkbox" label="message" default="0"
						   name="enable_message" onchange="">

					</field>

									</fields>				</fields>				</fields>				</config>